{"nm":"Line Globe Icon Animated","ddd":0,"h":600,"w":800,"meta":{"a":"Ision Industries","k":"#IconAnimation, #GlobeIcon, #AnimatedIcon","d":"Your users can experience traveling the world with this simple animated line globe","g":"LottieFiles AE 0.1.20"},"layers":[{"ty":0,"nm":"Line Globe Icon","sr":1.49,"st":0,"op":180.29,"ip":0,"hd":false,"ddd":0,"bm":0,"hasMask":false,"ao":0,"ks":{"a":{"a":0,"k":[400,300,0],"ix":1},"s":{"a":0,"k":[100,100,100],"ix":6},"sk":{"a":0,"k":0},"p":{"a":0,"k":[400,300,0],"ix":2},"r":{"a":0,"k":0,"ix":10},"sa":{"a":0,"k":0},"o":{"a":0,"k":100,"ix":11}},"ef":[],"w":800,"h":600,"refId":"comp_0","ind":1}],"v":"5.5.7","fr":60,"op":180,"ip":0,"assets":[{"nm":"","id":"comp_0","layers":[{"ty":4,"nm":"Vertical Curve 3","sr":1,"st":40,"op":121,"ip":40,"hd":false,"ddd":0,"bm":0,"hasMask":false,"ao":0,"ks":{"a":{"a":0,"k":[0.25,-0.875,0],"ix":1},"s":{"a":0,"k":[100,100,100],"ix":6},"sk":{"a":0,"k":0},"p":{"a":0,"k":[400,300,0],"ix":2},"r":{"a":0,"k":0,"ix":10},"sa":{"a":0,"k":0},"o":{"a":0,"k":100,"ix":11}},"ef":[],"shapes":[{"ty":"gr","bm":0,"hd":false,"mn":"ADBE Vector Group","nm":"Shape 2","ix":1,"cix":2,"np":3,"it":[{"ty":"sh","bm":0,"hd":false,"mn":"ADBE Vector Shape - Group","nm":"Path 1","ix":1,"d":1,"ks":{"a":1,"k":[{"o":{"x":0.167,"y":0.167},"i":{"x":0.833,"y":0.833},"s":[{"c":false,"i":[[0,0],[0,38.5],[-68.375,0]],"o":[[-69.75,0],[0,-40.75],[0,0]],"v":[[1,97.625],[-98.75,-0.625],[0.875,-99.5]]}],"t":90.75},{"s":[{"c":false,"i":[[0,0],[0.21,37.75],[-18.219,11.375]],"o":[[-25.219,-18.5],[-0.25,-45],[0,0]],"v":[[0.219,97.375],[-47,-0.625],[0.219,-99.5]]}],"t":121}],"ix":2}},{"ty":"st","bm":0,"hd":false,"mn":"ADBE Vector Graphic - Stroke","nm":"Stroke 1","lc":2,"lj":1,"ml":4,"o":{"a":0,"k":100,"ix":4},"w":{"a":0,"k":6,"ix":5},"c":{"a":0,"k":[1,1,1],"ix":3}},{"ty":"tr","a":{"a":0,"k":[0,0],"ix":1},"s":{"a":0,"k":[100,100],"ix":3},"sk":{"a":0,"k":0,"ix":4},"p":{"a":0,"k":[0,0],"ix":2},"r":{"a":0,"k":0,"ix":6},"sa":{"a":0,"k":0,"ix":5},"o":{"a":1,"k":[{"o":{"x":0.167,"y":0.167},"i":{"x":0.833,"y":0.833},"s":[0],"t":92.262},{"s":[100],"t":93.775390625}],"ix":7}}]},{"ty":"gr","bm":0,"hd":false,"mn":"ADBE Vector Group","nm":"Shape 1","ix":2,"cix":2,"np":3,"it":[{"ty":"sh","bm":0,"hd":false,"mn":"ADBE Vector Shape - Group","nm":"Path 1","ix":1,"d":1,"ks":{"a":1,"k":[{"o":{"x":0.167,"y":0.167},"i":{"x":0.833,"y":0.833},"s":[{"c":false,"i":[[0,0],[0,38.5],[-68.375,0]],"o":[[-69.75,0],[0,-40.75],[0,0]],"v":[[1,97.625],[-98.75,-0.625],[0.875,-99.5]]}],"t":60.5},{"o":{"x":0.167,"y":0.167},"i":{"x":0.833,"y":0.833},"s":[{"c":false,"i":[[0,0],[0.21,37.75],[-18.219,11.375]],"o":[[-25.219,-18.5],[-0.25,-45],[0,0]],"v":[[0.219,97.375],[-47,-0.625],[0.219,-99.5]]}],"t":90.75},{"s":[{"c":false,"i":[[0,0],[0,40.75],[21.531,15.875]],"o":[[21.031,-13.5],[0,-45.001],[0,0]],"v":[[0.219,97.375],[47.625,-0.625],[0.219,-99.5]]}],"t":121}],"ix":2}},{"ty":"st","bm":0,"hd":false,"mn":"ADBE Vector Graphic - Stroke","nm":"Stroke 1","lc":2,"lj":1,"ml":4,"o":{"a":0,"k":100,"ix":4},"w":{"a":0,"k":6,"ix":5},"c":{"a":0,"k":[1,1,1],"ix":3}},{"ty":"tr","a":{"a":0,"k":[0,0],"ix":1},"s":{"a":0,"k":[100,100],"ix":3},"sk":{"a":0,"k":0,"ix":4},"p":{"a":0,"k":[0,0],"ix":2},"r":{"a":0,"k":0,"ix":6},"sa":{"a":0,"k":0,"ix":5},"o":{"a":1,"k":[{"o":{"x":0.167,"y":0.167},"i":{"x":0.833,"y":0.833},"s":[0],"t":62.012},{"s":[100],"t":63.525390625}],"ix":7}}]}],"ind":1},{"ty":4,"nm":"Vertical Curve 2","sr":1,"st":0,"op":121,"ip":0,"hd":false,"ddd":0,"bm":0,"hasMask":false,"ao":0,"ks":{"a":{"a":0,"k":[0.25,-0.875,0],"ix":1},"s":{"a":0,"k":[100,100,100],"ix":6},"sk":{"a":0,"k":0},"p":{"a":0,"k":[400,300,0],"ix":2},"r":{"a":0,"k":0,"ix":10},"sa":{"a":0,"k":0},"o":{"a":0,"k":100,"ix":11}},"ef":[],"shapes":[{"ty":"gr","bm":0,"hd":false,"mn":"ADBE Vector Group","nm":"Shape 2","ix":1,"cix":2,"np":3,"it":[{"ty":"sh","bm":0,"hd":false,"mn":"ADBE Vector Shape - Group","nm":"Path 1","ix":1,"d":1,"ks":{"a":1,"k":[{"o":{"x":0.167,"y":0.167},"i":{"x":0.833,"y":0.833},"s":[{"c":false,"i":[[0,0],[0,40.75],[21.531,15.875]],"o":[[21.031,-13.5],[0,-45.001],[0,0]],"v":[[0.219,97.375],[47.625,-0.625],[0.219,-99.5]]}],"t":0},{"s":[{"c":false,"i":[[0,0],[0,44.25],[65.531,0]],"o":[[64.281,0],[0,-43.25],[0,0]],"v":[[0.219,97.375],[99.125,-0.624],[0.219,-99.5]]}],"t":30.25}],"ix":2}},{"ty":"st","bm":0,"hd":false,"mn":"ADBE Vector Graphic - Stroke","nm":"Stroke 1","lc":2,"lj":1,"ml":4,"o":{"a":0,"k":100,"ix":4},"w":{"a":0,"k":6,"ix":5},"c":{"a":0,"k":[1,1,1],"ix":3}},{"ty":"tr","a":{"a":0,"k":[0,0],"ix":1},"s":{"a":0,"k":[100,100],"ix":3},"sk":{"a":0,"k":0,"ix":4},"p":{"a":0,"k":[0,0],"ix":2},"r":{"a":0,"k":0,"ix":6},"sa":{"a":0,"k":0,"ix":5},"o":{"a":1,"k":[{"o":{"x":0.167,"y":0.167},"i":{"x":0.833,"y":0.833},"s":[100],"t":28.738},{"s":[0],"t":30.25}],"ix":7}}]},{"ty":"gr","bm":0,"hd":false,"mn":"ADBE Vector Group","nm":"Shape 1","ix":2,"cix":2,"np":3,"it":[{"ty":"sh","bm":0,"hd":false,"mn":"ADBE Vector Shape - Group","nm":"Path 1","ix":1,"d":1,"ks":{"a":1,"k":[{"o":{"x":0.167,"y":0.167},"i":{"x":0.833,"y":0.833},"s":[{"c":false,"i":[[0,0],[0.21,37.75],[-18.219,11.375]],"o":[[-25.219,-18.5],[-0.25,-45],[0,0]],"v":[[0.219,97.375],[-47,-0.625],[0.219,-99.5]]}],"t":0},{"o":{"x":0.167,"y":0.167},"i":{"x":0.833,"y":0.833},"s":[{"c":false,"i":[[0,0],[0,40.75],[21.531,15.875]],"o":[[21.031,-13.5],[0,-45.001],[0,0]],"v":[[0.219,97.375],[47.625,-0.625],[0.219,-99.5]]}],"t":30.25},{"s":[{"c":false,"i":[[0,0],[0,44.25],[65.531,0]],"o":[[64.281,0],[0,-43.25],[0,0]],"v":[[0.219,97.375],[99.125,-0.624],[0.219,-99.5]]}],"t":60.5}],"ix":2}},{"ty":"st","bm":0,"hd":false,"mn":"ADBE Vector Graphic - Stroke","nm":"Stroke 1","lc":2,"lj":1,"ml":4,"o":{"a":0,"k":100,"ix":4},"w":{"a":0,"k":6,"ix":5},"c":{"a":0,"k":[1,1,1],"ix":3}},{"ty":"tr","a":{"a":0,"k":[0,0],"ix":1},"s":{"a":0,"k":[100,100],"ix":3},"sk":{"a":0,"k":0,"ix":4},"p":{"a":0,"k":[0,0],"ix":2},"r":{"a":0,"k":0,"ix":6},"sa":{"a":0,"k":0,"ix":5},"o":{"a":1,"k":[{"o":{"x":0.167,"y":0.167},"i":{"x":0.833,"y":0.833},"s":[100],"t":58.988},{"s":[0],"t":60.5}],"ix":7}}]}],"ind":2},{"ty":4,"nm":"Vertical Curve 1","sr":1,"st":0,"op":121,"ip":0,"hd":false,"ddd":0,"bm":0,"hasMask":false,"ao":0,"ks":{"a":{"a":0,"k":[0.25,-0.875,0],"ix":1},"s":{"a":0,"k":[100,100,100],"ix":6},"sk":{"a":0,"k":0},"p":{"a":0,"k":[400,300,0],"ix":2},"r":{"a":0,"k":0,"ix":10},"sa":{"a":0,"k":0},"o":{"a":0,"k":100,"ix":11}},"ef":[],"shapes":[{"ty":"gr","bm":0,"hd":false,"mn":"ADBE Vector Group","nm":"Shape 2","ix":1,"cix":2,"np":3,"it":[{"ty":"sh","bm":0,"hd":false,"mn":"ADBE Vector Shape - Group","nm":"Path 1","ix":1,"d":1,"ks":{"a":1,"k":[{"o":{"x":0.167,"y":0.167},"i":{"x":0.833,"y":0.833},"s":[{"c":false,"i":[[0,0],[0,38.5],[-68.375,0]],"o":[[-69.75,0],[0,-40.75],[0,0]],"v":[[1,97.625],[-98.75,-0.625],[0.875,-99.5]]}],"t":30.25},{"o":{"x":0.167,"y":0.167},"i":{"x":0.833,"y":0.833},"s":[{"c":false,"i":[[0,0],[0.21,37.75],[-18.219,11.375]],"o":[[-25.219,-18.5],[-0.25,-45],[0,0]],"v":[[0.219,97.375],[-47,-0.625],[0.219,-99.5]]}],"t":60.5},{"o":{"x":0.167,"y":0.167},"i":{"x":0.833,"y":0.833},"s":[{"c":false,"i":[[0,0],[0,40.75],[21.531,15.875]],"o":[[21.031,-13.5],[0,-45.001],[0,0]],"v":[[0.219,97.375],[47.625,-0.625],[0.219,-99.5]]}],"t":90.75},{"s":[{"c":false,"i":[[0,0],[0,44.25],[65.531,0]],"o":[[64.281,0],[0,-43.25],[0,0]],"v":[[0.219,97.375],[99.125,-0.624],[0.219,-99.5]]}],"t":121}],"ix":2}},{"ty":"st","bm":0,"hd":false,"mn":"ADBE Vector Graphic - Stroke","nm":"Stroke 1","lc":2,"lj":1,"ml":4,"o":{"a":0,"k":100,"ix":4},"w":{"a":0,"k":6,"ix":5},"c":{"a":0,"k":[1,1,1],"ix":3}},{"ty":"tr","a":{"a":0,"k":[0,0],"ix":1},"s":{"a":0,"k":[100,100],"ix":3},"sk":{"a":0,"k":0,"ix":4},"p":{"a":0,"k":[0,0],"ix":2},"r":{"a":0,"k":0,"ix":6},"sa":{"a":0,"k":0,"ix":5},"o":{"a":1,"k":[{"o":{"x":0.167,"y":0.167},"i":{"x":0.833,"y":0.833},"s":[0],"t":31.762},{"o":{"x":0.167,"y":0.167},"i":{"x":0.833,"y":0.833},"s":[100],"t":33.275},{"o":{"x":0.167,"y":0.167},"i":{"x":0.833,"y":0.833},"s":[100],"t":119.488},{"s":[0],"t":121}],"ix":7}}]},{"ty":"gr","bm":0,"hd":false,"mn":"ADBE Vector Group","nm":"Shape 1","ix":2,"cix":2,"np":3,"it":[{"ty":"sh","bm":0,"hd":false,"mn":"ADBE Vector Shape - Group","nm":"Path 1","ix":1,"d":1,"ks":{"a":1,"k":[{"o":{"x":0.167,"y":0.167},"i":{"x":0.833,"y":0.833},"s":[{"c":false,"i":[[0,0],[0,38.5],[-68.375,0]],"o":[[-69.75,0],[0,-40.75],[0,0]],"v":[[1,97.625],[-98.75,-0.625],[0.875,-99.5]]}],"t":0},{"o":{"x":0.167,"y":0.167},"i":{"x":0.833,"y":0.833},"s":[{"c":false,"i":[[0,0],[0.21,37.75],[-18.219,11.375]],"o":[[-25.219,-18.5],[-0.25,-45],[0,0]],"v":[[0.219,97.375],[-47,-0.625],[0.219,-99.5]]}],"t":30.25},{"o":{"x":0.167,"y":0.167},"i":{"x":0.833,"y":0.833},"s":[{"c":false,"i":[[0,0],[0,40.75],[21.531,15.875]],"o":[[21.031,-13.5],[0,-45.001],[0,0]],"v":[[0.219,97.375],[47.625,-0.625],[0.219,-99.5]]}],"t":60.5},{"s":[{"c":false,"i":[[0,0],[0,44.25],[65.531,0]],"o":[[64.281,0],[0,-43.25],[0,0]],"v":[[0.219,97.375],[99.125,-0.624],[0.219,-99.5]]}],"t":90.75}],"ix":2}},{"ty":"st","bm":0,"hd":false,"mn":"ADBE Vector Graphic - Stroke","nm":"Stroke 1","lc":2,"lj":1,"ml":4,"o":{"a":0,"k":100,"ix":4},"w":{"a":0,"k":6,"ix":5},"c":{"a":0,"k":[1,1,1],"ix":3}},{"ty":"tr","a":{"a":0,"k":[0,0],"ix":1},"s":{"a":0,"k":[100,100],"ix":3},"sk":{"a":0,"k":0,"ix":4},"p":{"a":0,"k":[0,0],"ix":2},"r":{"a":0,"k":0,"ix":6},"sa":{"a":0,"k":0,"ix":5},"o":{"a":1,"k":[{"o":{"x":0.167,"y":0.167},"i":{"x":0.833,"y":0.833},"s":[0],"t":1.512},{"o":{"x":0.167,"y":0.167},"i":{"x":0.833,"y":0.833},"s":[100],"t":3.025},{"o":{"x":0.167,"y":0.167},"i":{"x":0.833,"y":0.833},"s":[100],"t":89.238},{"s":[0],"t":90.75}],"ix":7}}]}],"ind":3},{"ty":4,"nm":"Bottom Horizontal Curve","sr":1,"st":0,"op":121,"ip":0,"hd":false,"ddd":0,"bm":0,"hasMask":false,"ao":0,"ks":{"a":{"a":0,"k":[-0.25,-0.75,0],"ix":1},"s":{"a":0,"k":[-100,100,100],"ix":6},"sk":{"a":0,"k":0},"p":{"a":0,"k":[400,367.5,0],"ix":2},"r":{"a":0,"k":90,"ix":10},"sa":{"a":0,"k":0},"o":{"a":0,"k":100,"ix":11}},"ef":[],"shapes":[{"ty":"gr","bm":0,"hd":false,"mn":"ADBE Vector Group","nm":"Shape 1","ix":1,"cix":2,"np":3,"it":[{"ty":"sh","bm":0,"hd":false,"mn":"ADBE Vector Shape - Group","nm":"Path 1","ix":1,"d":1,"ks":{"a":0,"k":{"c":false,"i":[[0,0],[0,-43.438],[0,0]],"o":[[0,0],[0,39.688],[0,0]],"v":[[-0.25,-71.375],[22.25,-0.719],[-0.25,70.375]]},"ix":2}},{"ty":"st","bm":0,"hd":false,"mn":"ADBE Vector Graphic - Stroke","nm":"Stroke 1","lc":1,"lj":1,"ml":4,"o":{"a":0,"k":100,"ix":4},"w":{"a":0,"k":6,"ix":5},"c":{"a":0,"k":[1,1,1],"ix":3}},{"ty":"tr","a":{"a":0,"k":[0,0],"ix":1},"s":{"a":0,"k":[100,100],"ix":3},"sk":{"a":0,"k":0,"ix":4},"p":{"a":0,"k":[0,0],"ix":2},"r":{"a":0,"k":0,"ix":6},"sa":{"a":0,"k":0,"ix":5},"o":{"a":0,"k":100,"ix":7}}]}],"ind":4},{"ty":4,"nm":"Top Horizontal Curve","sr":1,"st":0,"op":121,"ip":0,"hd":false,"ddd":0,"bm":0,"hasMask":false,"ao":0,"ks":{"a":{"a":0,"k":[-0.25,-0.75,0],"ix":1},"s":{"a":0,"k":[100,100,100],"ix":6},"sk":{"a":0,"k":0},"p":{"a":0,"k":[400,232.5,0],"ix":2},"r":{"a":0,"k":90,"ix":10},"sa":{"a":0,"k":0},"o":{"a":0,"k":100,"ix":11}},"ef":[],"shapes":[{"ty":"gr","bm":0,"hd":false,"mn":"ADBE Vector Group","nm":"Shape 1","ix":1,"cix":2,"np":3,"it":[{"ty":"sh","bm":0,"hd":false,"mn":"ADBE Vector Shape - Group","nm":"Path 1","ix":1,"d":1,"ks":{"a":0,"k":{"c":false,"i":[[0,0],[0,-43.438],[0,0]],"o":[[0,0],[0,39.688],[0,0]],"v":[[-0.25,-71.375],[22.25,-0.719],[-0.25,70.375]]},"ix":2}},{"ty":"st","bm":0,"hd":false,"mn":"ADBE Vector Graphic - Stroke","nm":"Stroke 1","lc":1,"lj":1,"ml":4,"o":{"a":0,"k":100,"ix":4},"w":{"a":0,"k":6,"ix":5},"c":{"a":0,"k":[1,1,1],"ix":3}},{"ty":"tr","a":{"a":0,"k":[0,0],"ix":1},"s":{"a":0,"k":[100,100],"ix":3},"sk":{"a":0,"k":0,"ix":4},"p":{"a":0,"k":[0,0],"ix":2},"r":{"a":0,"k":0,"ix":6},"sa":{"a":0,"k":0,"ix":5},"o":{"a":0,"k":100,"ix":7}}]}],"ind":5},{"ty":4,"nm":"Middle Horizontal Line","sr":1,"st":0,"op":121,"ip":0,"hd":false,"ddd":0,"bm":0,"hasMask":false,"ao":0,"ks":{"a":{"a":0,"k":[-0.25,-0.75,0],"ix":1},"s":{"a":0,"k":[100,100,100],"ix":6},"sk":{"a":0,"k":0},"p":{"a":0,"k":[400,300,0],"ix":2},"r":{"a":0,"k":90,"ix":10},"sa":{"a":0,"k":0},"o":{"a":0,"k":100,"ix":11}},"ef":[],"shapes":[{"ty":"gr","bm":0,"hd":false,"mn":"ADBE Vector Group","nm":"Shape 1","ix":1,"cix":2,"np":3,"it":[{"ty":"sh","bm":0,"hd":false,"mn":"ADBE Vector Shape - Group","nm":"Path 1","ix":1,"d":1,"ks":{"a":0,"k":{"c":false,"i":[[0,0],[0,0]],"o":[[0,0],[0,0]],"v":[[-0.25,-98.5],[-0.25,97]]},"ix":2}},{"ty":"st","bm":0,"hd":false,"mn":"ADBE Vector Graphic - Stroke","nm":"Stroke 1","lc":1,"lj":1,"ml":4,"o":{"a":0,"k":100,"ix":4},"w":{"a":0,"k":6,"ix":5},"c":{"a":0,"k":[1,1,1],"ix":3}},{"ty":"tr","a":{"a":0,"k":[0,0],"ix":1},"s":{"a":0,"k":[100,100],"ix":3},"sk":{"a":0,"k":0,"ix":4},"p":{"a":0,"k":[0,0],"ix":2},"r":{"a":0,"k":0,"ix":6},"sa":{"a":0,"k":0,"ix":5},"o":{"a":0,"k":100,"ix":7}}]}],"ind":6},{"ty":4,"nm":"Outer Circle","sr":1,"st":0,"op":121,"ip":0,"hd":false,"ddd":0,"bm":0,"hasMask":false,"ao":0,"ks":{"a":{"a":0,"k":[0.25,-0.5,0],"ix":1},"s":{"a":0,"k":[100,100,100],"ix":6},"sk":{"a":0,"k":0},"p":{"a":0,"k":[400,300,0],"ix":2},"r":{"a":0,"k":0,"ix":10},"sa":{"a":0,"k":0},"o":{"a":0,"k":100,"ix":11}},"ef":[],"shapes":[{"ty":"gr","bm":0,"hd":false,"mn":"ADBE Vector Group","nm":"Ellipse 1","ix":1,"cix":2,"np":3,"it":[{"ty":"el","bm":0,"hd":false,"mn":"ADBE Vector Shape - Ellipse","nm":"Ellipse Path 1","d":1,"p":{"a":0,"k":[0,0],"ix":3},"s":{"a":0,"k":[197.445,197.445],"ix":2}},{"ty":"st","bm":0,"hd":false,"mn":"ADBE Vector Graphic - Stroke","nm":"Stroke 1","lc":1,"lj":1,"ml":4,"o":{"a":0,"k":100,"ix":4},"w":{"a":0,"k":6,"ix":5},"c":{"a":0,"k":[1,1,1],"ix":3}},{"ty":"tr","a":{"a":0,"k":[0,0],"ix":1},"s":{"a":0,"k":[100,100],"ix":3},"sk":{"a":0,"k":0,"ix":4},"p":{"a":0,"k":[0.25,-0.5],"ix":2},"r":{"a":0,"k":0,"ix":6},"sa":{"a":0,"k":0,"ix":5},"o":{"a":0,"k":100,"ix":7}}]}],"ind":7}]}]}